[{"anker":"<a class='page-info' href='https://metropool.nl/agenda'>metropool main - Mercenary & HateSphere</a>","errors":[],"title":"Mercenary & HateSphere","venueEventUrl":"https://metropool.nl/agenda/mercenary-plus-hatesphere/","shortText":"","unavailable":false,"soldOut":false},{"anker":"<a class='page-info' href='https://metropool.nl/agenda'>metropool main - Physical Graffiti</a>","errors":[],"title":"Physical Graffiti","venueEventUrl":"https://metropool.nl/agenda/physical-graffiti-hengelo/","shortText":"","unavailable":false,"soldOut":false},{"anker":"<a class='page-info' href='https://metropool.nl/agenda'>metropool main - The Toy Dolls</a>","errors":[],"title":"The Toy Dolls","venueEventUrl":"https://metropool.nl/agenda/the-toy-dolls/","shortText":"","unavailable":false,"soldOut":true},{"anker":"<a class='page-info' href='https://metropool.nl/agenda'>metropool main - Slope</a>","errors":[],"title":"Slope","venueEventUrl":"https://metropool.nl/agenda/slope/","shortText":"","unavailable":false,"soldOut":false},{"anker":"<a class='page-info' href='https://metropool.nl/agenda'>metropool main - Serenity</a>","errors":[],"title":"Serenity","venueEventUrl":"https://metropool.nl/agenda/serenity-22-feb/","shortText":"","unavailable":false,"soldOut":false},{"anker":"<a class='page-info' href='https://metropool.nl/agenda'>metropool main - Therion</a>","errors":[],"title":"Therion","venueEventUrl":"https://metropool.nl/agenda/therion/","shortText":"","unavailable":false,"soldOut":false},{"anker":"<a class='page-info' href='https://metropool.nl/agenda'>metropool main - Clan Of Xymox</a>","errors":[],"title":"Clan Of Xymox","venueEventUrl":"https://metropool.nl/agenda/clan-of-xymox/","shortText":"","unavailable":false,"soldOut":true},{"anker":"<a class='page-info' href='https://metropool.nl/agenda'>metropool main - Ares</a>","errors":[],"title":"Ares","venueEventUrl":"https://metropool.nl/agenda/ares/","shortText":"","unavailable":false,"soldOut":true},{"anker":"<a class='page-info' href='https://metropool.nl/agenda'>metropool main - Gallus</a>","errors":[],"title":"Gallus","venueEventUrl":"https://metropool.nl/agenda/gallus/","shortText":"","unavailable":false,"soldOut":false},{"anker":"<a class='page-info' href='https://metropool.nl/agenda'>metropool main - Saga</a>","errors":[],"title":"Saga","venueEventUrl":"https://metropool.nl/agenda/saga-enschede/","shortText":"","unavailable":false,"soldOut":false},{"anker":"<a class='page-info' href='https://metropool.nl/agenda'>metropool main - Denial of Life + Negative Frame</a>","errors":[],"title":"Denial of Life + Negative Frame","venueEventUrl":"https://metropool.nl/agenda/denial-of-life-plus-negative-frame/","shortText":"","unavailable":false,"soldOut":false},{"anker":"<a class='page-info' href='https://metropool.nl/agenda'>metropool main - Filter</a>","errors":[],"title":"Filter","venueEventUrl":"https://metropool.nl/agenda/filter/","shortText":"alternative metal, alternative rock, grunge, industrial metal, nu metal, post-grunge","unavailable":false,"soldOut":false},{"anker":"<a class='page-info' href='https://metropool.nl/agenda'>metropool main - Julian Sas</a>","errors":[],"title":"Julian Sas","venueEventUrl":"https://metropool.nl/agenda/julian-sas-enschede/","shortText":"","unavailable":false,"soldOut":false},{"anker":"<a class='page-info' href='https://metropool.nl/agenda'>metropool main - CARNIFEX</a>","errors":[],"title":"CARNIFEX","venueEventUrl":"https://metropool.nl/agenda/carnifex/","shortText":"","unavailable":false,"soldOut":false},{"anker":"<a class='page-info' href='https://metropool.nl/agenda'>metropool main - VLTIMAS</a>","errors":[],"title":"VLTIMAS","venueEventUrl":"https://metropool.nl/agenda/vltimas-enschede/","shortText":"","unavailable":false,"soldOut":false},{"anker":"<a class='page-info' href='https://metropool.nl/agenda'>metropool main - LORDI</a>","errors":[],"title":"LORDI","venueEventUrl":"https://metropool.nl/agenda/lordi/","shortText":"","unavailable":false,"soldOut":false},{"anker":"<a class='page-info' href='https://metropool.nl/agenda'>metropool main - Angelus Apatrida</a>","errors":[],"title":"Angelus Apatrida","venueEventUrl":"https://metropool.nl/agenda/angelus-apatrida/","shortText":"","unavailable":false,"soldOut":false},{"anker":"<a class='page-info' href='https://metropool.nl/agenda'>metropool main - Status Quotes</a>","errors":[],"title":"Status Quotes","venueEventUrl":"https://metropool.nl/agenda/status-quotes-2024/","shortText":"","unavailable":false,"soldOut":false},{"anker":"<a class='page-info' href='https://metropool.nl/agenda'>metropool main - Subsignal</a>","errors":[],"title":"Subsignal","venueEventUrl":"https://metropool.nl/agenda/subsignal/","shortText":"german prog, progressive metal","unavailable":false,"soldOut":false},{"anker":"<a class='page-info' href='https://metropool.nl/agenda'>metropool main - Pene Corrida</a>","errors":[],"title":"Pene Corrida","venueEventUrl":"https://metropool.nl/agenda/pene-corrida/","shortText":"","unavailable":false,"soldOut":false},{"anker":"<a class='page-info' href='https://metropool.nl/agenda'>metropool main - Matt Schofield</a>","errors":[],"title":"Matt Schofield","venueEventUrl":"https://metropool.nl/agenda/matt-schofield/","shortText":"","unavailable":false,"soldOut":false},{"anker":"<a class='page-info' href='https://metropool.nl/agenda'>metropool main - Limehouse Lizzy</a>","errors":[],"title":"Limehouse Lizzy","venueEventUrl":"https://metropool.nl/agenda/limehouse-lizzy/","shortText":"","unavailable":false,"soldOut":false},{"anker":"<a class='page-info' href='https://metropool.nl/agenda'>metropool main - Riot V</a>","errors":[],"title":"Riot V","venueEventUrl":"https://metropool.nl/agenda/riot-v/","shortText":"","unavailable":false,"soldOut":false},{"anker":"<a class='page-info' href='https://metropool.nl/agenda'>metropool main - Misery Index + Schizophrenia </a>","errors":[],"title":"Misery Index + Schizophrenia ","venueEventUrl":"https://metropool.nl/agenda/misery-index-plus-schizophrenia/","shortText":"","unavailable":false,"soldOut":false},{"anker":"<a class='page-info' href='https://metropool.nl/agenda'>metropool main - Apes of the State</a>","errors":[],"title":"Apes of the State","venueEventUrl":"https://metropool.nl/agenda/apes-of-the-state/","shortText":"","unavailable":false,"soldOut":false},{"anker":"<a class='page-info' href='https://metropool.nl/agenda'>metropool main - Vanaheim + Xaon + End of the Dream </a>","errors":[],"title":"Vanaheim + Xaon + End of the Dream ","venueEventUrl":"https://metropool.nl/agenda/vanaheim-plus-xaon-plus-end-of-the-dream/","shortText":"","unavailable":false,"soldOut":false},{"anker":"<a class='page-info' href='https://metropool.nl/agenda'>metropool main - Richie Kotzen</a>","errors":[],"title":"Richie Kotzen","venueEventUrl":"https://metropool.nl/agenda/richie-kotzen/","shortText":"","unavailable":false,"soldOut":false},{"anker":"<a class='page-info' href='https://metropool.nl/agenda'>metropool main - Witching</a>","errors":[],"title":"Witching","venueEventUrl":"https://metropool.nl/agenda/witching/","shortText":"","unavailable":false,"soldOut":false},{"anker":"<a class='page-info' href='https://metropool.nl/agenda'>metropool main - dEUS</a>","errors":[],"title":"dEUS","venueEventUrl":"https://metropool.nl/agenda/deus/","shortText":"","unavailable":false,"soldOut":false},{"anker":"<a class='page-info' href='https://metropool.nl/agenda'>metropool main - The Smiths Presumably</a>","errors":[],"title":"The Smiths Presumably","venueEventUrl":"https://metropool.nl/agenda/the-smiths-presumably/","shortText":"","unavailable":false,"soldOut":false},{"anker":"<a class='page-info' href='https://metropool.nl/agenda'>metropool main - Kissin' Dynamite</a>","errors":[],"title":"Kissin' Dynamite","venueEventUrl":"https://metropool.nl/agenda/kissin-dynamite-enschede/","shortText":"","unavailable":false,"soldOut":false},{"anker":"<a class='page-info' href='https://metropool.nl/agenda'>metropool main - We Love Dark Music</a>","errors":[],"title":"We Love Dark Music","venueEventUrl":"https://metropool.nl/agenda/we-love-dark-music/","shortText":"","unavailable":false,"soldOut":false}]