[
  {
    "doorOpenDateTime": null,
    "startDateTime": "2023-05-20T18:00:00.000Z",
    "endDateTime": null,
    "venueEventUrl": "https://www.afaslive.nl/agenda/the-offspring",
    "title": "The Offspring",
    "location": "afaslive",
    "price": 49.28,
    "shortText": null,
    "longText": "../public/texts/b207a446-69dd-4e34-85f3-ee25071c023d.html",
    "image": "https://www.afaslive.nl/files/Agenda/2023/05-Mei/_agendaitem/The-Offspring.jpg",
    "soldOut": true
  },
  {
    "doorOpenDateTime": null,
    "startDateTime": "2023-10-06T18:00:00.000Z",
    "endDateTime": null,
    "venueEventUrl": "https://www.afaslive.nl/agenda/inhaler",
    "title": "Inhaler",
    "location": "afaslive",
    "price": 33.6,
    "shortText": null,
    "longText": "../public/texts/f27252a6-b81a-4763-817d-0b4bf0fadea6.html",
    "image": "https://www.afaslive.nl/files/Agenda/2023/10-Oktober/_agendaitem/Inhaler.jpg",
    "soldOut": false
  },
  {
    "doorOpenDateTime": null,
    "startDateTime": "2023-10-24T18:00:00.000Z",
    "endDateTime": null,
    "venueEventUrl": "https://www.afaslive.nl/agenda/fall-out-boy",
    "title": "Fall Out Boy",
    "location": "afaslive",
    "price": 57.12,
    "shortText": null,
    "longText": "../public/texts/6d501cce-5eec-4476-9c99-eba61fb11451.html",
    "image": "https://www.afaslive.nl/files/Agenda/2023/10-Oktober/_agendaitem/Fall-Out-Boy.jpg",
    "soldOut": false
  },
  {
    "doorOpenDateTime": null,
    "startDateTime": "2023-11-15T19:00:00.000Z",
    "endDateTime": null,
    "venueEventUrl": "https://www.afaslive.nl/agenda/jungle-1",
    "title": "Jungle",
    "location": "afaslive",
    "price": 44.8,
    "shortText": null,
    "longText": "../public/texts/75944282-341a-4813-a209-a04b2cf2bcc8.html",
    "image": "https://www.afaslive.nl/files/Agenda/2023/11-November/_agendaitem/Jungle-2.jpg",
    "soldOut": false
  },
  {
    "doorOpenDateTime": null,
    "startDateTime": "2023-11-30T19:00:00.000Z",
    "endDateTime": null,
    "venueEventUrl": "https://www.afaslive.nl/agenda/sting-2",
    "title": "Sting",
    "location": "afaslive",
    "price": 88.48,
    "shortText": null,
    "longText": "../public/texts/16d125f3-a55d-444c-849b-0e0ebed6bd1f.html",
    "image": "https://www.afaslive.nl/files/Agenda/2023/_agendaitem/Sting.jpg",
    "soldOut": true
  }
]