[
  {
    "doorOpenDateTime": "2022-12-15T18:00:00.000Z",
    "startDateTime": "2022-12-15T18:30:00.000Z",
    "endDateTime": null,
    "venueEventUrl": "https://www.013.nl/programma/7361/danko-jones",
    "title": "Danko Jones",
    "location": "013",
    "price": 25.9,
    "shortText": "",
    "longText": "../public/texts/0238fb8e-3fc9-42b1-851a-c335edcadee0.html",
    "image": "https://www.013.nl/uploads/cache/event_main_desktop/6315f704bd881.png?version=1662383963"
  },
  {
    "doorOpenDateTime": "2023-01-11T19:00:00.000Z",
    "startDateTime": "2023-01-11T19:45:00.000Z",
    "endDateTime": null,
    "venueEventUrl": "https://www.013.nl/programma/7427/cats-cult",
    "title": "Cat's Cult",
    "location": "013",
    "price": null,
    "shortText": "FIEP + Rats and Daggers",
    "longText": "../public/texts/24276d35-0c00-46ea-b86a-37f957f2989b.html",
    "image": "https://www.013.nl/uploads/cache/event_main_desktop/636bcf0bd12e5.jpg?version=1668009758"
  },
  {
    "doorOpenDateTime": "2023-01-22T18:00:00.000Z",
    "startDateTime": "2023-01-22T19:00:00.000Z",
    "endDateTime": null,
    "venueEventUrl": "https://www.013.nl/programma/7358/bruce-dickinson",
    "title": "Bruce Dickinson",
    "location": "013",
    "price": 48.4,
    "shortText": "An Evening with Bruce Dickinson",
    "longText": "../public/texts/d74e4494-2bfb-4eec-8d0b-eec879d4d88f.html",
    "image": "https://www.013.nl/uploads/cache/event_main_desktop/6324424ea036f.jpg?version=1663320669"
  },
  {
    "doorOpenDateTime": "2023-02-08T19:00:00.000Z",
    "startDateTime": "2023-02-08T19:45:00.000Z",
    "endDateTime": null,
    "venueEventUrl": "https://www.013.nl/programma/7428/cats-cult",
    "title": "Cat's Cult",
    "location": "013",
    "price": null,
    "shortText": "TAPE TOY + Bongloard",
    "longText": "../public/texts/44d46a60-c1c6-4b0d-9d71-4cff486875d8.html",
    "image": "https://www.013.nl/uploads/cache/event_main_desktop/636bcc967e477.jpg?version=1668009141"
  },
  {
    "doorOpenDateTime": "2023-02-26T18:00:00.000Z",
    "startDateTime": "2023-02-26T18:30:00.000Z",
    "endDateTime": null,
    "venueEventUrl": "https://www.013.nl/programma/7387/neptunian-maximalism",
    "title": "Neptunian Maximalism",
    "location": "013",
    "price": 16.4,
    "shortText": "& its Supernova Arkestra",
    "longText": "../public/texts/88171c23-935b-4add-9217-3951092b24f4.html",
    "image": "https://www.013.nl/uploads/cache/event_main_desktop/62a6f0c7964ee.jpg?version=1655107794"
  },
  {
    "doorOpenDateTime": "2023-03-03T18:00:00.000Z",
    "startDateTime": "2023-03-03T19:00:00.000Z",
    "endDateTime": null,
    "venueEventUrl": "https://www.013.nl/programma/7277/devin-townsend",
    "title": "Devin Townsend",
    "location": "013",
    "price": 36.9,
    "shortText": "",
    "longText": "../public/texts/4b0134bc-92ad-46b8-8461-0852ba623cb0.html",
    "image": "https://www.013.nl/uploads/cache/event_main_desktop/62a203e618b3b.jpg?version=1654785578"
  },
  {
    "doorOpenDateTime": "2023-03-10T18:00:00.000Z",
    "startDateTime": "2023-03-10T18:30:00.000Z",
    "endDateTime": null,
    "venueEventUrl": "https://www.013.nl/programma/7420/navarone",
    "title": "Navarone",
    "location": "013",
    "price": 27.9,
    "shortText": "",
    "longText": "../public/texts/ae7d4c1d-0911-4caf-9ca4-74eca05d69af.html",
    "image": "https://www.013.nl/uploads/cache/event_main_desktop/63637c03395a0.jpg?version=1667464384"
  },
  {
    "doorOpenDateTime": "2023-03-16T18:30:00.000Z",
    "startDateTime": "2023-03-16T19:00:00.000Z",
    "endDateTime": null,
    "venueEventUrl": "https://www.013.nl/programma/7323/ferocious-dog",
    "title": "Ferocious Dog",
    "location": "013",
    "price": 17.9,
    "shortText": "",
    "longText": "../public/texts/f08e5aea-ab16-4dab-bb05-9cf0d34ec58d.html",
    "image": "https://www.013.nl/uploads/cache/event_main_desktop/62e9159c885c6.jpg?version=1659442605"
  },
  {
    "doorOpenDateTime": "2023-03-22T17:30:00.000Z",
    "startDateTime": "2023-03-22T18:30:00.000Z",
    "endDateTime": null,
    "venueEventUrl": "https://www.013.nl/programma/7355/haken-between-the-buried-and-me",
    "title": "Haken + Between The Buried And Me",
    "location": "013",
    "price": 34.4,
    "shortText": "Island In Limbo Tour",
    "longText": "../public/texts/f84ef6f7-7cf3-4587-919e-57113952897a.html",
    "image": "https://www.013.nl/uploads/cache/event_main_desktop/6304a3dc1cc8a.jpg?version=1661248484"
  },
  {
    "doorOpenDateTime": "2023-04-12T17:00:00.000Z",
    "startDateTime": "2023-04-12T18:00:00.000Z",
    "endDateTime": null,
    "venueEventUrl": "https://www.013.nl/programma/7295/floor-jansen",
    "title": "Floor Jansen",
    "location": "013",
    "price": 38.4,
    "shortText": "",
    "longText": "../public/texts/222be43c-512e-4760-998d-167f654d30cb.html",
    "image": "https://www.013.nl/uploads/cache/event_main_desktop/62a051f9d42f1.jpg?version=1655379810"
  },
  {
    "doorOpenDateTime": "2023-04-20T11:00:00.000Z",
    "startDateTime": "2023-04-20T11:00:00.000Z",
    "endDateTime": null,
    "venueEventUrl": "https://www.013.nl/programma/7438/roadburn-festival-2023",
    "title": "Roadburn Festival 2023",
    "location": "013",
    "price": null,
    "shortText": "Redefining heaviness",
    "longText": "../public/texts/296378a0-68d9-4ae9-ba40-20deec58d022.html",
    "image": "https://www.013.nl/uploads/cache/event_main_desktop/6372184fdbb03.jpg?version=1668422376"
  },
  {
    "doorOpenDateTime": "2023-06-05T17:00:00.000Z",
    "startDateTime": "2023-06-05T18:00:00.000Z",
    "endDateTime": null,
    "venueEventUrl": "https://www.013.nl/programma/7344/turnstile",
    "title": "Turnstile",
    "location": "013",
    "price": 42.3,
    "shortText": "",
    "longText": "../public/texts/502cbb42-552f-464c-ad6b-051d7b48e366.html",
    "image": "https://www.013.nl/uploads/cache/event_main_desktop/638f57240273e.jpg?version=1670338344"
  },
  {
    "doorOpenDateTime": "2023-09-16T17:00:00.000Z",
    "startDateTime": "2023-09-16T18:15:00.000Z",
    "endDateTime": null,
    "venueEventUrl": "https://www.013.nl/programma/7399/ayreon",
    "title": "Ayreon",
    "location": "013",
    "price": 70,
    "shortText": "- 01011001 - Live Beneath the Waves",
    "longText": "../public/texts/6dab19e8-82b2-46ce-9dbc-9fba86af7717.html",
    "image": "https://www.013.nl/uploads/cache/event_main_desktop/6346b267d7970.jpg?version=1665639188"
  }
]