[
  {
    "doorOpenDateTime": "2022-09-16T18:00:00.000Z",
    "startDateTime": "2022-09-16T18:30:00.000Z",
    "endDateTime": null,
    "venueEventUrl": "https://www.013.nl/programma/7301/tides-from-nebula",
    "title": "Tides from Nebula",
    "location": "013",
    "price": 14.9,
    "shortText": null,
    "longText": "../public/texts/508afdf6-598c-4f8d-862b-6e863f10e28b.html",
    "image": "https://www.013.nl/uploads/cache/event_main_desktop/62a847fa6b095.jpg?version=1655195706"
  },
  {
    "doorOpenDateTime": "2022-09-30T17:00:00.000Z",
    "startDateTime": "2022-09-30T17:30:00.000Z",
    "endDateTime": null,
    "venueEventUrl": "https://www.013.nl/programma/6807/vola",
    "title": "Vola",
    "location": "013",
    "price": 18.9,
    "shortText": null,
    "longText": "../public/texts/9d16c64d-ea39-4399-8e40-556a112585e0.html",
    "image": "https://www.013.nl/uploads/cache/event_main_desktop/61f806bfd753d.jpg?version=1646386756"
  },
  {
    "doorOpenDateTime": "2022-10-06T17:00:00.000Z",
    "startDateTime": "2022-10-06T17:30:00.000Z",
    "endDateTime": null,
    "venueEventUrl": "https://www.013.nl/programma/7309/sumac",
    "title": "SUMAC",
    "location": "013",
    "price": 19.9,
    "shortText": null,
    "longText": "../public/texts/2a829598-074d-424c-97b9-22ea1d3c76cb.html",
    "image": "https://www.013.nl/uploads/cache/event_main_desktop/62bac288350d0.jpg?version=1656406750"
  },
  {
    "doorOpenDateTime": "2022-10-12T18:00:00.000Z",
    "startDateTime": "2022-10-12T18:30:00.000Z",
    "endDateTime": null,
    "venueEventUrl": "https://www.013.nl/programma/7331/cats-cult",
    "title": "Cat's Cult",
    "location": "013",
    "price": "12",
    "shortText": "Bony Macaroni + Hey Team",
    "longText": "../public/texts/f8de7dbd-9b41-48b8-8d18-917d47217069.html",
    "image": "https://www.013.nl/uploads/cache/event_main_desktop/62ebb80628292.jpg?version=1659615389"
  },
  {
    "doorOpenDateTime": "2022-10-19T17:30:00.000Z",
    "startDateTime": "2022-10-19T18:00:00.000Z",
    "endDateTime": null,
    "venueEventUrl": "https://www.013.nl/programma/6733/aaron-turner",
    "title": "Aaron Turner",
    "location": "013",
    "price": 15.9,
    "shortText": null,
    "longText": "../public/texts/bb6e310b-51cf-4638-bc51-83bfe29ea3f1.html",
    "image": "https://www.013.nl/uploads/cache/event_main_desktop/62a1cd797b497.jpg?version=1654771137"
  },
  {
    "doorOpenDateTime": "2022-10-30T17:30:00.000Z",
    "startDateTime": "2022-10-30T18:30:00.000Z",
    "endDateTime": null,
    "venueEventUrl": "https://www.013.nl/programma/7167/ministry",
    "title": "Ministry",
    "location": "013",
    "price": 39.4,
    "shortText": null,
    "longText": "../public/texts/7c5203bf-748e-4537-be52-c06bb2cafc95.html",
    "image": "https://www.013.nl/uploads/cache/event_main_desktop/62384e5eec85d.jpg?version=1653648191"
  },
  {
    "doorOpenDateTime": "2022-11-12T19:00:00.000Z",
    "startDateTime": "2022-11-12T19:30:00.000Z",
    "endDateTime": null,
    "venueEventUrl": "https://www.013.nl/programma/7325/crown-compass",
    "title": "Crown Compass",
    "location": "013",
    "price": 14.9,
    "shortText": null,
    "longText": "../public/texts/921245e4-2af1-4294-8e65-ab6c94af782b.html",
    "image": "https://www.013.nl/uploads/cache/event_main_desktop/62ea5028ef32f.jpg?version=1659523232"
  },
  {
    "doorOpenDateTime": "2022-11-17T18:00:00.000Z",
    "startDateTime": "2022-11-17T18:30:00.000Z",
    "endDateTime": null,
    "venueEventUrl": "https://www.013.nl/programma/6617/steve-n-seagulls",
    "title": "Steve 'n' Seagulls",
    "location": "013",
    "price": 21.9,
    "shortText": null,
    "longText": "../public/texts/a6507dad-4b16-4ce2-a1c2-de75b2d1cbfe.html",
    "image": "https://www.013.nl/uploads/cache/event_main_desktop/5e6a3f2eb9b86.jpg?version=1646386758"
  },
  {
    "doorOpenDateTime": "2022-11-23T18:00:00.000Z",
    "startDateTime": "2022-11-23T19:00:00.000Z",
    "endDateTime": null,
    "venueEventUrl": "https://www.013.nl/programma/7203/billy-talent",
    "title": "Billy Talent",
    "location": "013",
    "price": 40.49,
    "shortText": null,
    "longText": "../public/texts/3f4eb708-a9c9-4dc5-8b38-c899abd096cc.html",
    "image": "https://www.013.nl/uploads/cache/event_main_desktop/628e055c20435.jpg?version=1654266889"
  },
  {
    "doorOpenDateTime": "2022-11-29T16:00:00.000Z",
    "startDateTime": "2022-11-29T17:00:00.000Z",
    "endDateTime": null,
    "venueEventUrl": "https://www.013.nl/programma/6839/lamb-of-god-kreator",
    "title": "Lamb of God + Kreator",
    "location": "013",
    "price": 45.4,
    "shortText": null,
    "longText": "../public/texts/c2618f03-9846-4e03-b4e6-da45ebd23144.html",
    "image": "https://www.013.nl/uploads/cache/event_main_desktop/61793840aae97.png?version=1646386758"
  },
  {
    "doorOpenDateTime": "2022-12-19T17:30:00.000Z",
    "startDateTime": "2022-12-19T18:30:00.000Z",
    "endDateTime": null,
    "venueEventUrl": "https://www.013.nl/programma/7273/airbourne",
    "title": "Airbourne",
    "location": "013",
    "price": 34.4,
    "shortText": null,
    "longText": "../public/texts/f719338b-86f7-49c8-b05e-eab59b7326e1.html",
    "image": "https://www.013.nl/uploads/cache/event_main_desktop/628b65980f8b2.jpg?version=1656336601"
  },
  {
    "doorOpenDateTime": "2023-01-19T18:00:00.000Z",
    "startDateTime": "2023-01-19T19:00:00.000Z",
    "endDateTime": null,
    "venueEventUrl": "https://www.013.nl/programma/7183/karnivool",
    "title": "Karnivool",
    "location": "013",
    "price": 25.4,
    "shortText": null,
    "longText": "../public/texts/d159b1a2-bfac-4eba-aa79-2ecccdeb123e.html",
    "image": "https://www.013.nl/uploads/cache/event_main_desktop/5fbc10e14e362.jpg?version=1646386746"
  },
  {
    "doorOpenDateTime": "2023-02-16T18:00:00.000Z",
    "startDateTime": "2023-02-16T18:30:00.000Z",
    "endDateTime": null,
    "venueEventUrl": "https://www.013.nl/programma/7366/long-distance-calling",
    "title": "Long Distance Calling",
    "location": "013",
    "price": 19.9,
    "shortText": null,
    "longText": "../public/texts/76adb371-33ee-438c-a9ab-9fb5bee219c5.html",
    "image": "https://www.013.nl/uploads/cache/event_main_desktop/631894addb951.jpg?version=1662558061"
  },
  {
    "doorOpenDateTime": "2023-03-03T18:00:00.000Z",
    "startDateTime": "2023-03-03T19:00:00.000Z",
    "endDateTime": null,
    "venueEventUrl": "https://www.013.nl/programma/7277/devin-townsend",
    "title": "Devin Townsend",
    "location": "013",
    "price": 36.9,
    "shortText": null,
    "longText": "../public/texts/ebbf19db-4a64-40cd-8e6c-e2d632df9efe.html",
    "image": "https://www.013.nl/uploads/cache/event_main_desktop/62a203e618b3b.jpg?version=1654785578"
  },
  {
    "doorOpenDateTime": "2023-03-16T18:30:00.000Z",
    "startDateTime": "2023-03-16T19:00:00.000Z",
    "endDateTime": null,
    "venueEventUrl": "https://www.013.nl/programma/7323/ferocious-dog",
    "title": "Ferocious Dog",
    "location": "013",
    "price": 17.9,
    "shortText": null,
    "longText": "../public/texts/c7306182-849e-42da-a853-50d2c172a165.html",
    "image": "https://www.013.nl/uploads/cache/event_main_desktop/62e9159c885c6.jpg?version=1659442605"
  },
  {
    "doorOpenDateTime": "2023-04-14T17:00:00.000Z",
    "startDateTime": "2023-04-14T18:00:00.000Z",
    "endDateTime": null,
    "venueEventUrl": "https://www.013.nl/programma/7345/delain",
    "title": "Delain",
    "location": "013",
    "price": 26.9,
    "shortText": null,
    "longText": "../public/texts/2886d2ba-777d-46a2-b927-ba789754d6d1.html",
    "image": "https://www.013.nl/uploads/cache/event_main_desktop/62f4ce79a3632.jpg?version=1660210919"
  }
]