[
  {
    "doorOpenDateTime": null,
    "startDateTime": "2023-09-08T18:30:00.000Z",
    "endDateTime": "2023-09-08T18:00:00.000Z",
    "venueEventUrl": "https://www.podiumdeflux.nl/events/symphonic-metal-nights/",
    "title": "SYMPHONIC METAL NIGHTS",
    "location": "deflux",
    "shortText": null,
    "longText": "../public/texts/aa005114-76b4-4d66-a234-aa60f067cb14.html",
    "image": "https://www.podiumdeflux.nl/wp-content/uploads/2023/05/SIRENIA-01-scaled.jpg",
    "soldOut": null,
    "unavailable": "",
    "corrupted": null,
    "origin": "deflux"
  },
  {
    "doorOpenDateTime": null,
    "startDateTime": "2023-07-07T18:00:00.000Z",
    "endDateTime": "2023-07-07T17:30:00.000Z",
    "venueEventUrl": "https://www.podiumdeflux.nl/events/nh-metal-fest/",
    "title": "NH Metal Fest",
    "location": "deflux",
    "shortText": null,
    "longText": "../public/texts/2d6fc758-3541-4cc3-9f4a-fb3ac12608cc.html",
    "image": "https://www.podiumdeflux.nl/wp-content/uploads/2023/04/WhatsApp-Image-2023-04-19-at-08.45.34.jpeg",
    "soldOut": null,
    "unavailable": "",
    "corrupted": null,
    "origin": "deflux"
  },
  {
    "doorOpenDateTime": null,
    "startDateTime": "2023-07-21T22:00:00.000Z",
    "endDateTime": null,
    "venueEventUrl": "https://www.podiumdeflux.nl/events/haltpop-2023/",
    "title": "HALTPOP 2023",
    "location": "deflux",
    "shortText": null,
    "longText": "../public/texts/954c0d8f-a1b6-4fa8-8cea-c5b221146893.html",
    "image": "https://www.podiumdeflux.nl/wp-content/uploads/2023/04/HP23.jpg",
    "soldOut": null,
    "unavailable": "",
    "corrupted": null,
    "origin": "deflux"
  },
  {
    "doorOpenDateTime": null,
    "startDateTime": "2022-11-04T19:30:00.000Z",
    "endDateTime": "2022-11-04T19:00:00.000Z",
    "venueEventUrl": "https://www.podiumdeflux.nl/events/hard-met-bar-stool-preachers-svetlanas/",
    "title": "HARD! met Bar Stool Preachers &#038; Svetlanas",
    "location": "deflux",
    "shortText": null,
    "longText": "../public/texts/abe4eb2d-9f3d-406c-b188-b94940bf0458.html",
    "image": "https://www.podiumdeflux.nl/wp-content/uploads/2022/10/5.-HARD-Bar-Stool-Preachers-Persfoto-scaled.jpeg",
    "soldOut": null,
    "unavailable": "",
    "corrupted": null,
    "origin": "deflux"
  },
  {
    "doorOpenDateTime": null,
    "startDateTime": "2022-12-09T17:30:00.000Z",
    "endDateTime": "2022-12-09T17:30:00.000Z",
    "venueEventUrl": "https://www.podiumdeflux.nl/events/haltpop-winterfest/",
    "title": "HALTPOP WINTERFEST",
    "location": "deflux",
    "shortText": null,
    "longText": "../public/texts/2f9aa55e-f8ae-4180-a5b0-da92453452bd.html",
    "image": "https://www.podiumdeflux.nl/wp-content/uploads/2022/09/Winterfest22_Poster-scaled.jpg",
    "soldOut": null,
    "unavailable": "",
    "corrupted": null,
    "origin": "deflux"
  },
  {
    "doorOpenDateTime": null,
    "startDateTime": "2022-11-09T19:00:00.000Z",
    "endDateTime": "2022-11-09T19:00:00.000Z",
    "venueEventUrl": "https://www.podiumdeflux.nl/events/keep-of-kalessin-dhg-cadaver/",
    "title": "Keep Of Kalessin, DHG &#038; Cadaver &#8211; Exclusieve NL show",
    "location": "deflux",
    "shortText": null,
    "longText": "../public/texts/16164dee-3ae4-4a1d-8c14-d77724dbcf1f.html",
    "image": "https://www.podiumdeflux.nl/wp-content/uploads/2022/09/Instagram_Image.jpg",
    "soldOut": null,
    "unavailable": "",
    "corrupted": null,
    "origin": "deflux"
  },
  {
    "doorOpenDateTime": null,
    "startDateTime": "2022-10-14T18:30:00.000Z",
    "endDateTime": "2022-10-14T18:00:00.000Z",
    "venueEventUrl": "https://www.podiumdeflux.nl/events/hard-met-consolation-monolith-deathcult-burial-remains/",
    "title": "HARD! Met Consolation, Monolith Deathcult &#038; Burial Remains",
    "location": "deflux",
    "shortText": null,
    "longText": "../public/texts/72dd8d1f-cfad-4a0b-a44d-df8b1d8124e7.html",
    "image": "https://www.podiumdeflux.nl/wp-content/uploads/2022/08/HARD-Met-Consolation-Banner-scaled.jpg",
    "soldOut": null,
    "unavailable": "",
    "corrupted": null,
    "origin": "deflux"
  },
  {
    "doorOpenDateTime": null,
    "startDateTime": "2023-04-15T18:30:00.000Z",
    "endDateTime": "2023-04-15T18:00:00.000Z",
    "venueEventUrl": "https://www.podiumdeflux.nl/events/de-kift-feest-van-het-hondsvot/",
    "title": "De Kift &#8211; Flux op locatie",
    "location": "deflux",
    "shortText": null,
    "longText": "../public/texts/eac5c88a-dc73-432b-bb5e-43c8d2667603.html",
    "image": "https://www.podiumdeflux.nl/wp-content/uploads/2022/07/DeKift-let-op-naamvermelding-forograaf-verplicht-Christophe-Vico-min-scaled.jpeg",
    "soldOut": null,
    "unavailable": "",
    "corrupted": null,
    "origin": "deflux"
  },
  {
    "doorOpenDateTime": null,
    "startDateTime": "2022-11-24T18:00:00.000Z",
    "endDateTime": "2022-11-24T17:30:00.000Z",
    "venueEventUrl": "https://www.podiumdeflux.nl/events/leaves-eyes-special-guests-catalyst-crime-temperance/",
    "title": "Leaves&#8217; Eyes + Special Guests: Catalyst Crime &#038; Temperance",
    "location": "deflux",
    "shortText": null,
    "longText": "../public/texts/7d7bec5c-e70f-47d3-9f2c-0d7e4fb0a4d4.html",
    "image": "https://www.podiumdeflux.nl/wp-content/uploads/2022/06/LE_TLV_P02_copyrightStefanHeilemann-min-scaled.jpeg",
    "soldOut": null,
    "unavailable": "",
    "corrupted": null,
    "origin": "deflux"
  },
  {
    "doorOpenDateTime": null,
    "startDateTime": "2022-07-16T14:00:00.000Z",
    "endDateTime": "2022-07-16T14:00:00.000Z",
    "venueEventUrl": "https://www.podiumdeflux.nl/events/haltpop-2022/",
    "title": "HALTPOP 2022",
    "location": "deflux",
    "shortText": null,
    "longText": "../public/texts/dabc6fb0-c04c-4344-90c1-0cc448f311a0.html",
    "image": "https://www.podiumdeflux.nl/wp-content/uploads/2022/05/IMG_8622.jpg",
    "soldOut": null,
    "unavailable": "",
    "corrupted": null,
    "origin": "deflux"
  }
]